cookiecutter_exersise/__init__.py
cookiecutter_exersise/cookiecutter_exersise.py
cookiecutter_exersise-0.2.5.dist-info/AUTHORS.rst
cookiecutter_exersise-0.2.5.dist-info/LICENSE
cookiecutter_exersise-0.2.5.dist-info/METADATA
cookiecutter_exersise-0.2.5.dist-info/WHEEL
cookiecutter_exersise-0.2.5.dist-info/top_level.txt
cookiecutter_exersise-0.2.5.dist-info/RECORD
