Metadata-Version: 2.1
Name: cookiecutter-exersise
Version: 0.2.5
Summary: Example of coockiecutter using
Home-page: https://github.com/ilionesso/cookiecutter_exersise
Author: Ileko Shia
Author-email: ololo@azaza.kek
License: MIT license
Keywords: cookiecutter_exersise
Platform: UNKNOWN
Classifier: Development Status :: 2 - Pre-Alpha
Classifier: Intended Audience :: Developers
Classifier: License :: OSI Approved :: MIT License
Classifier: Natural Language :: English
Classifier: Programming Language :: Python :: 2
Classifier: Programming Language :: Python :: 2.7
Classifier: Programming Language :: Python :: 3
Classifier: Programming Language :: Python :: 3.5
Classifier: Programming Language :: Python :: 3.6
Classifier: Programming Language :: Python :: 3.7
Classifier: Programming Language :: Python :: 3.8
Requires-Python: >=2.7, !=3.0.*, !=3.1.*, !=3.2.*, !=3.3.*, !=3.4.*
